finalsa/common/calendar/__init__.py
finalsa/common/calendar/calendar.py
finalsa_common_calendar-0.1.0.dist-info/METADATA
finalsa_common_calendar-0.1.0.dist-info/WHEEL
finalsa_common_calendar-0.1.0.dist-info/licenses/LICENSE.md
finalsa_common_calendar-0.1.0.dist-info/RECORD
