Metadata-Version: 2.4
Name: finalsa-common-calendar
Version: 0.1.0
Summary: Common calendar utilities for Finalsa projects
Project-URL: Homepage, https://github.com/finalsa/finalsa-common-calendar
Author-email: Luis Jimenez <luis@finalsa.com>
License: MIT License
License-File: LICENSE.md
Keywords: aws,client,dynamodb
Requires-Python: >=3.10
Requires-Dist: pytz>=2025.1
